{
    "_meta":  {
                  "objectType":  "flow",
                  "module":  "WorkflowCommons",
                  "qualifiedName":  "WorkflowCommons.SUB_Workflow_CountCompletedOnTime",
                  "stableId":  "ba393c62-77c8-4ec8-bff0-62d9ef312160",
                  "slug":  "workflowcommons-sub-workflow-countcompletedontime",
                  "l0Path":  "knowledge-base/modules/_marktplace/WorkflowCommons/flows/workflowcommons-sub-workflow-countcompletedontime.abstract.md",
                  "l1Path":  "knowledge-base/modules/_marktplace/WorkflowCommons/flows/workflowcommons-sub-workflow-countcompletedontime.overview.md",
                  "l2Path":  "app-overview/current/modules/marketplace/WorkflowCommons/flows/workflowcommons-sub-workflow-countcompletedontime.json",
                  "l2Logical":  "flow:WorkflowCommons.SUB_Workflow_CountCompletedOnTime",
                  "sourceRun":  "cli_2026-03-14T09-23-46.259Z",
                  "aggregateJson":  "app-overview/cli_2026-03-14T09-23-46.259Z/modules/marketplace/WorkflowCommons/flows.json",
                  "aggregatePseudo":  "app-overview/cli_2026-03-14T09-23-46.259Z/modules/marketplace/WorkflowCommons/flows.pseudo.txt",
                  "collectionIndex":  "app-overview/current/modules/marketplace/WorkflowCommons/flows/INDEX.json"
              },
    "flowId":  "ba393c62-77c8-4ec8-bff0-62d9ef312160",
    "kind":  "Microflow",
    "qualifiedName":  "WorkflowCommons.SUB_Workflow_CountCompletedOnTime",
    "module":  "WorkflowCommons",
    "nodes":  [
                  {
                      "nodeId":  "e9be690b-aa7a-4e9d-8ce4-aac6eacc68af",
                      "nodeType":  "ActionActivity",
                      "label":  "AggregateListAction: AggregateListAction (output=CountCompletedOnTime, errorHandlingType=Rollback)",
                      "detail":  "AggregateListAction (output=CountCompletedOnTime, errorHandlingType=Rollback)",
                      "loopOwnerId":  null,
                      "isExecutable":  true,
                      "calls":  [

                                ]
                  },
                  {
                      "nodeId":  "c7aacd1f-50e7-4e8d-9933-85c2daad8035",
                      "nodeType":  "ActionActivity",
                      "label":  "CreateVariableAction: create variable IgnoreCompletedAfter=$CompletedAfter = empty",
                      "detail":  "create variable IgnoreCompletedAfter=$CompletedAfter = empty",
                      "loopOwnerId":  null,
                      "isExecutable":  true,
                      "calls":  [

                                ]
                  },
                  {
                      "nodeId":  "95928433-9010-4ab3-a812-fb10a9a49d10",
                      "nodeType":  "ActionActivity",
                      "label":  "CreateVariableAction: create variable IgnoreCompletedBefore=$CompletedBefore = empty",
                      "detail":  "create variable IgnoreCompletedBefore=$CompletedBefore = empty",
                      "loopOwnerId":  null,
                      "isExecutable":  true,
                      "calls":  [

                                ]
                  },
                  {
                      "nodeId":  "ac2b6f3b-c825-4db6-84cd-0926d33f8740",
                      "nodeType":  "ActionActivity",
                      "label":  "RetrieveAction: retrieve WorkflowView_CompletedOnTime from WorkflowCommons.WorkflowView",
                      "detail":  "retrieve WorkflowView_CompletedOnTime from WorkflowCommons.WorkflowView",
                      "loopOwnerId":  null,
                      "isExecutable":  true,
                      "calls":  [

                                ]
                  },
                  {
                      "nodeId":  "462f03cd-4445-4e1d-b03e-51e20fc50bad",
                      "nodeType":  "EndEvent",
                      "label":  "EndEvent",
                      "detail":  null,
                      "loopOwnerId":  null,
                      "isExecutable":  true,
                      "calls":  [

                                ]
                  },
                  {
                      "nodeId":  "2dd742af-31d7-4dd1-b3c8-8efde35be9ea",
                      "nodeType":  "MicroflowParameterObject",
                      "label":  "MicroflowParameterObject",
                      "detail":  null,
                      "loopOwnerId":  null,
                      "isExecutable":  false,
                      "calls":  [

                                ]
                  },
                  {
                      "nodeId":  "775493a4-46d8-47b3-9b3d-b7469a101b01",
                      "nodeType":  "MicroflowParameterObject",
                      "label":  "MicroflowParameterObject",
                      "detail":  null,
                      "loopOwnerId":  null,
                      "isExecutable":  false,
                      "calls":  [

                                ]
                  },
                  {
                      "nodeId":  "d49e5351-51e7-4dc8-b769-135abcacc3f1",
                      "nodeType":  "MicroflowParameterObject",
                      "label":  "MicroflowParameterObject",
                      "detail":  null,
                      "loopOwnerId":  null,
                      "isExecutable":  false,
                      "calls":  [

                                ]
                  },
                  {
                      "nodeId":  "f65a22fa-3421-4966-bd08-9c2cc4d44318",
                      "nodeType":  "StartEvent",
                      "label":  "StartEvent",
                      "detail":  null,
                      "loopOwnerId":  null,
                      "isExecutable":  true,
                      "calls":  [

                                ]
                  }
              ],
    "edges":  [
                  {
                      "edgeId":  "bd2b95c5-2f72-4bb8-9d77-c47234c30555",
                      "originNodeId":  "ac2b6f3b-c825-4db6-84cd-0926d33f8740",
                      "destinationNodeId":  "e9be690b-aa7a-4e9d-8ce4-aac6eacc68af",
                      "condition":  null,
                      "isErrorHandler":  false,
                      "originConnectionIndex":  1,
                      "destinationConnectionIndex":  3
                  },
                  {
                      "edgeId":  "75a83760-552e-4f22-9ae3-fdaa44acadca",
                      "originNodeId":  "f65a22fa-3421-4966-bd08-9c2cc4d44318",
                      "destinationNodeId":  "c7aacd1f-50e7-4e8d-9933-85c2daad8035",
                      "condition":  null,
                      "isErrorHandler":  false,
                      "originConnectionIndex":  1,
                      "destinationConnectionIndex":  3
                  },
                  {
                      "edgeId":  "9f7800c4-25d0-4ad4-a066-9fe1ce0de04d",
                      "originNodeId":  "e9be690b-aa7a-4e9d-8ce4-aac6eacc68af",
                      "destinationNodeId":  "462f03cd-4445-4e1d-b03e-51e20fc50bad",
                      "condition":  null,
                      "isErrorHandler":  false,
                      "originConnectionIndex":  1,
                      "destinationConnectionIndex":  3
                  },
                  {
                      "edgeId":  "91cd5d43-1eee-43f4-9446-3c7b0b8bfd06",
                      "originNodeId":  "c7aacd1f-50e7-4e8d-9933-85c2daad8035",
                      "destinationNodeId":  "95928433-9010-4ab3-a812-fb10a9a49d10",
                      "condition":  null,
                      "isErrorHandler":  false,
                      "originConnectionIndex":  1,
                      "destinationConnectionIndex":  3
                  },
                  {
                      "edgeId":  "20ed494c-394e-471c-857f-885949fe21d7",
                      "originNodeId":  "95928433-9010-4ab3-a812-fb10a9a49d10",
                      "destinationNodeId":  "ac2b6f3b-c825-4db6-84cd-0926d33f8740",
                      "condition":  null,
                      "isErrorHandler":  false,
                      "originConnectionIndex":  1,
                      "destinationConnectionIndex":  3
                  }
              ],
    "calls":  [

              ],
    "startNodeIds":  [
                         "f65a22fa-3421-4966-bd08-9c2cc4d44318"
                     ],
    "primaryExecutionOrderNodeIds":  [
                                         "f65a22fa-3421-4966-bd08-9c2cc4d44318",
                                         "c7aacd1f-50e7-4e8d-9933-85c2daad8035",
                                         "95928433-9010-4ab3-a812-fb10a9a49d10",
                                         "ac2b6f3b-c825-4db6-84cd-0926d33f8740",
                                         "e9be690b-aa7a-4e9d-8ce4-aac6eacc68af",
                                         "462f03cd-4445-4e1d-b03e-51e20fc50bad"
                                     ],
    "pseudocode":  "FLOW Microflow: WorkflowCommons.SUB_Workflow_CountCompletedOnTime\r\nNODES=9; EDGES=5\r\n1. START\r\n2. ACTION CreateVariableAction: create variable IgnoreCompletedAfter=$CompletedAfter = empty\r\n3. ACTION CreateVariableAction: create variable IgnoreCompletedBefore=$CompletedBefore = empty\r\n4. ACTION RetrieveAction: retrieve WorkflowView_CompletedOnTime from WorkflowCommons.WorkflowView\r\n5. ACTION AggregateListAction: AggregateListAction (output=CountCompletedOnTime, errorHandlingType=Rollback)\r\n6. END",
    "retrieveActions":  [
                            null
                        ],
    "decisionActions":  [
                            null
                        ],
    "showPageActions":  [
                            null
                        ],
    "mutationActions":  [
                            null
                        ],
    "callEdges":  [
                      {
                          "callerModule":  "WorkflowCommons",
                          "callerFlow":  "WorkflowCommons.SUB_WorkflowSeries_CreateOrUpdate",
                          "callerKind":  "Microflow",
                          "callKind":  "Microflow",
                          "sourceNodeId":  "e13e33bb-d557-4474-8349-f648f243fd54",
                          "targetModule":  "WorkflowCommons",
                          "targetFlow":  "WorkflowCommons.SUB_Workflow_CountCompletedOnTime",
                          "isInternal":  true
                      }
                  ]
}
