{
    "_meta":  {
                  "objectType":  "flow",
                  "module":  "ExcelImporter",
                  "qualifiedName":  "ExcelImporter.Column_SetCorrectRefObjectType",
                  "stableId":  "a69ce0bb-f6d7-4270-9f53-a77700eaa470",
                  "slug":  "excelimporter-column-setcorrectrefobjecttype",
                  "l0Path":  "knowledge-base/modules/_marktplace/ExcelImporter/flows/excelimporter-column-setcorrectrefobjecttype.abstract.md",
                  "l1Path":  "knowledge-base/modules/_marktplace/ExcelImporter/flows/excelimporter-column-setcorrectrefobjecttype.overview.md",
                  "l2Path":  "app-overview/current/modules/marketplace/ExcelImporter/flows/excelimporter-column-setcorrectrefobjecttype.json",
                  "l2Logical":  "flow:ExcelImporter.Column_SetCorrectRefObjectType",
                  "sourceRun":  "cli_2026-03-14T09-26-12.835Z",
                  "aggregateJson":  "app-overview/cli_2026-03-14T09-26-12.835Z/modules/marketplace/ExcelImporter/flows.json",
                  "aggregatePseudo":  "app-overview/cli_2026-03-14T09-26-12.835Z/modules/marketplace/ExcelImporter/flows.pseudo.txt",
                  "collectionIndex":  "app-overview/current/modules/marketplace/ExcelImporter/flows/INDEX.json"
              },
    "flowId":  "a69ce0bb-f6d7-4270-9f53-a77700eaa470",
    "kind":  "Microflow",
    "qualifiedName":  "ExcelImporter.Column_SetCorrectRefObjectType",
    "module":  "ExcelImporter",
    "nodes":  [
                  {
                      "nodeId":  "1c0853ea-4921-4042-85ba-5b41be71b4c0",
                      "nodeType":  "ActionActivity",
                      "label":  "AggregateListAction: AggregateListAction (output=NrOfObjects, errorHandlingType=Rollback)",
                      "detail":  "AggregateListAction (output=NrOfObjects, errorHandlingType=Rollback)",
                      "loopOwnerId":  null,
                      "isExecutable":  true,
                      "calls":  [

                                ]
                  },
                  {
                      "nodeId":  "8d87e0bb-71bd-44f3-9cf7-010002931dbe",
                      "nodeType":  "ActionActivity",
                      "label":  "ChangeObjectAction: change Column (Column_MxObjectType_Reference=$Iterator; refreshInClient=true)",
                      "detail":  "change Column (Column_MxObjectType_Reference=$Iterator; refreshInClient=true)",
                      "loopOwnerId":  "8d9b1c46-f2b6-4f96-b97c-f13d385c476c",
                      "isExecutable":  true,
                      "calls":  [

                                ]
                  },
                  {
                      "nodeId":  "3aa1daf2-99be-40b3-9fe1-bebc4c7d51c0",
                      "nodeType":  "ActionActivity",
                      "label":  "ChangeObjectAction: change Column (Column_MxObjectType_Reference=empty; refreshInClient=true)",
                      "detail":  "change Column (Column_MxObjectType_Reference=empty; refreshInClient=true)",
                      "loopOwnerId":  null,
                      "isExecutable":  true,
                      "calls":  [

                                ]
                  },
                  {
                      "nodeId":  "690bc5ec-245d-4bac-8a9e-74bc4a4cfe07",
                      "nodeType":  "ActionActivity",
                      "label":  "ListOperationAction: ListOperationAction (output=SelectionIsValid, errorHandlingType=Rollback)",
                      "detail":  "ListOperationAction (output=SelectionIsValid, errorHandlingType=Rollback)",
                      "loopOwnerId":  null,
                      "isExecutable":  true,
                      "calls":  [

                                ]
                  },
                  {
                      "nodeId":  "b992b918-d6f1-4d0e-819c-ddf2daf4e662",
                      "nodeType":  "ActionActivity",
                      "label":  "MicroflowCallAction: call microflow ExcelImporter.Ch_SetObjectType_Reference",
                      "detail":  "call microflow ExcelImporter.Ch_SetObjectType_Reference",
                      "loopOwnerId":  null,
                      "isExecutable":  true,
                      "calls":  [
                                    {
                                        "callKind":  "Microflow",
                                        "targetFlowName":  "ExcelImporter.Ch_SetObjectType_Reference",
                                        "sourceNodeId":  "b992b918-d6f1-4d0e-819c-ddf2daf4e662"
                                    }
                                ]
                  },
                  {
                      "nodeId":  "d1c1228a-77ec-4790-b3aa-410308d131cd",
                      "nodeType":  "ActionActivity",
                      "label":  "RetrieveAction: retrieve MxObjects from MxModelReflection.MxObjectType",
                      "detail":  "retrieve MxObjects from MxModelReflection.MxObjectType",
                      "loopOwnerId":  null,
                      "isExecutable":  true,
                      "calls":  [

                                ]
                  },
                  {
                      "nodeId":  "0325ea93-d672-4161-8238-ba3c98ebdfa0",
                      "nodeType":  "ActionActivity",
                      "label":  "RetrieveAction: retrieve MxObject_Ref over association Column_MxObjectType_Reference from Column",
                      "detail":  "retrieve MxObject_Ref over association Column_MxObjectType_Reference from Column",
                      "loopOwnerId":  null,
                      "isExecutable":  true,
                      "calls":  [

                                ]
                  },
                  {
                      "nodeId":  "71da5a80-5370-4150-ae0e-310264b063f9",
                      "nodeType":  "ContinueEvent",
                      "label":  "ContinueEvent",
                      "detail":  null,
                      "loopOwnerId":  "8d9b1c46-f2b6-4f96-b97c-f13d385c476c",
                      "isExecutable":  true,
                      "calls":  [

                                ]
                  },
                  {
                      "nodeId":  "3eed3513-8b57-476a-aab5-bd44f9e4a661",
                      "nodeType":  "EndEvent",
                      "label":  "EndEvent",
                      "detail":  null,
                      "loopOwnerId":  null,
                      "isExecutable":  true,
                      "calls":  [

                                ]
                  },
                  {
                      "nodeId":  "3f285824-5a25-4bba-bb9c-11e77669ed9f",
                      "nodeType":  "EndEvent",
                      "label":  "EndEvent",
                      "detail":  null,
                      "loopOwnerId":  null,
                      "isExecutable":  true,
                      "calls":  [

                                ]
                  },
                  {
                      "nodeId":  "fee4e1c9-f52a-40cd-a899-827595b3c526",
                      "nodeType":  "EndEvent",
                      "label":  "EndEvent",
                      "detail":  null,
                      "loopOwnerId":  null,
                      "isExecutable":  true,
                      "calls":  [

                                ]
                  },
                  {
                      "nodeId":  "4f7fadbd-d101-43f3-aead-25d4933eb016",
                      "nodeType":  "ExclusiveMerge",
                      "label":  "ExclusiveMerge",
                      "detail":  null,
                      "loopOwnerId":  null,
                      "isExecutable":  true,
                      "calls":  [

                                ]
                  },
                  {
                      "nodeId":  "ac78b7f8-0602-4c76-a9e6-49141f0dfccf",
                      "nodeType":  "ExclusiveSplit",
                      "label":  "\u003e 2 expression=$NrOfObjects \u003e 2",
                      "detail":  "\u003e 2 expression=$NrOfObjects \u003e 2",
                      "loopOwnerId":  null,
                      "isExecutable":  true,
                      "calls":  [

                                ]
                  },
                  {
                      "nodeId":  "db7d2bee-ae69-45ff-8419-400c676faff8",
                      "nodeType":  "ExclusiveSplit",
                      "label":  "already has objecttype? expression=$MxObject_Ref != empty",
                      "detail":  "already has objecttype? expression=$MxObject_Ref != empty",
                      "loopOwnerId":  null,
                      "isExecutable":  true,
                      "calls":  [

                                ]
                  },
                  {
                      "nodeId":  "c4fe81c5-b558-4474-8c15-5fef3c2e0c7a",
                      "nodeType":  "ExclusiveSplit",
                      "label":  "expression=$Iterator != $StartMxObjectType",
                      "detail":  "expression=$Iterator != $StartMxObjectType",
                      "loopOwnerId":  "8d9b1c46-f2b6-4f96-b97c-f13d385c476c",
                      "isExecutable":  true,
                      "calls":  [

                                ]
                  },
                  {
                      "nodeId":  "fc5ec24c-dd6c-4bb5-84eb-2da2d8d86e31",
                      "nodeType":  "ExclusiveSplit",
                      "label":  "valid? expression=$SelectionIsValid",
                      "detail":  "valid? expression=$SelectionIsValid",
                      "loopOwnerId":  null,
                      "isExecutable":  true,
                      "calls":  [

                                ]
                  },
                  {
                      "nodeId":  "8d9b1c46-f2b6-4f96-b97c-f13d385c476c",
                      "nodeType":  "LoopedActivity",
                      "label":  "iterate MxObjects as Iterator",
                      "detail":  "iterate MxObjects as Iterator",
                      "loopOwnerId":  null,
                      "isExecutable":  true,
                      "calls":  [

                                ]
                  },
                  {
                      "nodeId":  "6c4ff69b-b7aa-4f9a-a6ec-148c1b8db465",
                      "nodeType":  "MicroflowParameterObject",
                      "label":  "MicroflowParameterObject",
                      "detail":  null,
                      "loopOwnerId":  null,
                      "isExecutable":  false,
                      "calls":  [

                                ]
                  },
                  {
                      "nodeId":  "8e1dc65f-17a7-4a41-8362-b0a777a9f706",
                      "nodeType":  "MicroflowParameterObject",
                      "label":  "MicroflowParameterObject",
                      "detail":  null,
                      "loopOwnerId":  null,
                      "isExecutable":  false,
                      "calls":  [

                                ]
                  },
                  {
                      "nodeId":  "ac452ed5-908b-4873-935d-7f92d73c7914",
                      "nodeType":  "MicroflowParameterObject",
                      "label":  "MicroflowParameterObject",
                      "detail":  null,
                      "loopOwnerId":  null,
                      "isExecutable":  false,
                      "calls":  [

                                ]
                  },
                  {
                      "nodeId":  "0709bb78-8a80-41e8-ba31-783c3fd60c0f",
                      "nodeType":  "StartEvent",
                      "label":  "StartEvent",
                      "detail":  null,
                      "loopOwnerId":  null,
                      "isExecutable":  true,
                      "calls":  [

                                ]
                  }
              ],
    "edges":  [
                  {
                      "edgeId":  "c3b5b3ee-0756-4bec-a008-39135b26c638",
                      "originNodeId":  "d1c1228a-77ec-4790-b3aa-410308d131cd",
                      "destinationNodeId":  "0325ea93-d672-4161-8238-ba3c98ebdfa0",
                      "condition":  null,
                      "isErrorHandler":  false,
                      "originConnectionIndex":  1,
                      "destinationConnectionIndex":  3
                  },
                  {
                      "edgeId":  "da7a5e76-599e-46f0-911f-76c0edad094b",
                      "originNodeId":  "1c0853ea-4921-4042-85ba-5b41be71b4c0",
                      "destinationNodeId":  "ac78b7f8-0602-4c76-a9e6-49141f0dfccf",
                      "condition":  null,
                      "isErrorHandler":  false,
                      "originConnectionIndex":  1,
                      "destinationConnectionIndex":  3
                  },
                  {
                      "edgeId":  "89426493-dd99-4349-baa5-e7a12452cf07",
                      "originNodeId":  "ac78b7f8-0602-4c76-a9e6-49141f0dfccf",
                      "destinationNodeId":  "3aa1daf2-99be-40b3-9fe1-bebc4c7d51c0",
                      "condition":  "EnumerationCase=true",
                      "isErrorHandler":  false,
                      "originConnectionIndex":  1,
                      "destinationConnectionIndex":  3
                  },
                  {
                      "edgeId":  "73a7df09-7aed-4f59-8601-559d03b487ca",
                      "originNodeId":  "690bc5ec-245d-4bac-8a9e-74bc4a4cfe07",
                      "destinationNodeId":  "fc5ec24c-dd6c-4bb5-84eb-2da2d8d86e31",
                      "condition":  null,
                      "isErrorHandler":  false,
                      "originConnectionIndex":  1,
                      "destinationConnectionIndex":  3
                  },
                  {
                      "edgeId":  "f2144974-129f-414b-85aa-439938ff2888",
                      "originNodeId":  "db7d2bee-ae69-45ff-8419-400c676faff8",
                      "destinationNodeId":  "690bc5ec-245d-4bac-8a9e-74bc4a4cfe07",
                      "condition":  "EnumerationCase=true",
                      "isErrorHandler":  false,
                      "originConnectionIndex":  1,
                      "destinationConnectionIndex":  3
                  },
                  {
                      "edgeId":  "741d70e6-b173-4452-a198-ee3a443e0ab5",
                      "originNodeId":  "fc5ec24c-dd6c-4bb5-84eb-2da2d8d86e31",
                      "destinationNodeId":  "4f7fadbd-d101-43f3-aead-25d4933eb016",
                      "condition":  "EnumerationCase=false",
                      "isErrorHandler":  false,
                      "originConnectionIndex":  1,
                      "destinationConnectionIndex":  3
                  },
                  {
                      "edgeId":  "de950236-b025-4b05-84b2-91ac554c0bd8",
                      "originNodeId":  "fc5ec24c-dd6c-4bb5-84eb-2da2d8d86e31",
                      "destinationNodeId":  "3eed3513-8b57-476a-aab5-bd44f9e4a661",
                      "condition":  "EnumerationCase=true",
                      "isErrorHandler":  false,
                      "originConnectionIndex":  0,
                      "destinationConnectionIndex":  2
                  },
                  {
                      "edgeId":  "55a07106-2fc8-468c-a49c-e80998ff4939",
                      "originNodeId":  "ac78b7f8-0602-4c76-a9e6-49141f0dfccf",
                      "destinationNodeId":  "8d9b1c46-f2b6-4f96-b97c-f13d385c476c",
                      "condition":  "EnumerationCase=false",
                      "isErrorHandler":  false,
                      "originConnectionIndex":  2,
                      "destinationConnectionIndex":  0
                  },
                  {
                      "edgeId":  "b3cdd50b-8099-4ccc-88ac-18196b05ae30",
                      "originNodeId":  "c4fe81c5-b558-4474-8c15-5fef3c2e0c7a",
                      "destinationNodeId":  "8d87e0bb-71bd-44f3-9cf7-010002931dbe",
                      "condition":  "EnumerationCase=true",
                      "isErrorHandler":  false,
                      "originConnectionIndex":  1,
                      "destinationConnectionIndex":  3
                  },
                  {
                      "edgeId":  "a7fffb3a-f878-40f1-a531-85911e9b7309",
                      "originNodeId":  "c4fe81c5-b558-4474-8c15-5fef3c2e0c7a",
                      "destinationNodeId":  "71da5a80-5370-4150-ae0e-310264b063f9",
                      "condition":  "EnumerationCase=false",
                      "isErrorHandler":  false,
                      "originConnectionIndex":  0,
                      "destinationConnectionIndex":  3
                  },
                  {
                      "edgeId":  "e9667102-d2b3-4609-a254-89d0d619e23f",
                      "originNodeId":  "8d9b1c46-f2b6-4f96-b97c-f13d385c476c",
                      "destinationNodeId":  "b992b918-d6f1-4d0e-819c-ddf2daf4e662",
                      "condition":  null,
                      "isErrorHandler":  false,
                      "originConnectionIndex":  1,
                      "destinationConnectionIndex":  3
                  },
                  {
                      "edgeId":  "322545ec-95a4-452d-a176-94e0c274523d",
                      "originNodeId":  "db7d2bee-ae69-45ff-8419-400c676faff8",
                      "destinationNodeId":  "4f7fadbd-d101-43f3-aead-25d4933eb016",
                      "condition":  "EnumerationCase=false",
                      "isErrorHandler":  false,
                      "originConnectionIndex":  2,
                      "destinationConnectionIndex":  2
                  },
                  {
                      "edgeId":  "7b72da1b-e5b7-4feb-b5d7-ed86e245f78f",
                      "originNodeId":  "4f7fadbd-d101-43f3-aead-25d4933eb016",
                      "destinationNodeId":  "1c0853ea-4921-4042-85ba-5b41be71b4c0",
                      "condition":  null,
                      "isErrorHandler":  false,
                      "originConnectionIndex":  1,
                      "destinationConnectionIndex":  3
                  },
                  {
                      "edgeId":  "20e30bda-f44b-4729-abb7-84125e1a058a",
                      "originNodeId":  "3aa1daf2-99be-40b3-9fe1-bebc4c7d51c0",
                      "destinationNodeId":  "3f285824-5a25-4bba-bb9c-11e77669ed9f",
                      "condition":  null,
                      "isErrorHandler":  false,
                      "originConnectionIndex":  1,
                      "destinationConnectionIndex":  3
                  },
                  {
                      "edgeId":  "13d4ab6e-ac13-4b1d-8dc2-9d82986bf205",
                      "originNodeId":  "b992b918-d6f1-4d0e-819c-ddf2daf4e662",
                      "destinationNodeId":  "fee4e1c9-f52a-40cd-a899-827595b3c526",
                      "condition":  null,
                      "isErrorHandler":  false,
                      "originConnectionIndex":  1,
                      "destinationConnectionIndex":  3
                  },
                  {
                      "edgeId":  "0bfec495-9834-4c7c-9daa-cd906ecde7a1",
                      "originNodeId":  "0325ea93-d672-4161-8238-ba3c98ebdfa0",
                      "destinationNodeId":  "db7d2bee-ae69-45ff-8419-400c676faff8",
                      "condition":  null,
                      "isErrorHandler":  false,
                      "originConnectionIndex":  1,
                      "destinationConnectionIndex":  3
                  },
                  {
                      "edgeId":  "04627bf3-6a44-44be-a8ac-d20fe7f8b8dd",
                      "originNodeId":  "0709bb78-8a80-41e8-ba31-783c3fd60c0f",
                      "destinationNodeId":  "d1c1228a-77ec-4790-b3aa-410308d131cd",
                      "condition":  null,
                      "isErrorHandler":  false,
                      "originConnectionIndex":  1,
                      "destinationConnectionIndex":  3
                  }
              ],
    "calls":  [
                  {
                      "callKind":  "Microflow",
                      "targetFlowName":  "ExcelImporter.Ch_SetObjectType_Reference",
                      "sourceNodeId":  "b992b918-d6f1-4d0e-819c-ddf2daf4e662"
                  }
              ],
    "startNodeIds":  [
                         "0709bb78-8a80-41e8-ba31-783c3fd60c0f"
                     ],
    "primaryExecutionOrderNodeIds":  [
                                         "0709bb78-8a80-41e8-ba31-783c3fd60c0f",
                                         "d1c1228a-77ec-4790-b3aa-410308d131cd",
                                         "0325ea93-d672-4161-8238-ba3c98ebdfa0",
                                         "db7d2bee-ae69-45ff-8419-400c676faff8",
                                         "690bc5ec-245d-4bac-8a9e-74bc4a4cfe07",
                                         "fc5ec24c-dd6c-4bb5-84eb-2da2d8d86e31",
                                         "3eed3513-8b57-476a-aab5-bd44f9e4a661",
                                         "4f7fadbd-d101-43f3-aead-25d4933eb016",
                                         "1c0853ea-4921-4042-85ba-5b41be71b4c0",
                                         "ac78b7f8-0602-4c76-a9e6-49141f0dfccf",
                                         "3aa1daf2-99be-40b3-9fe1-bebc4c7d51c0",
                                         "3f285824-5a25-4bba-bb9c-11e77669ed9f",
                                         "8d9b1c46-f2b6-4f96-b97c-f13d385c476c",
                                         "71da5a80-5370-4150-ae0e-310264b063f9",
                                         "8d87e0bb-71bd-44f3-9cf7-010002931dbe",
                                         "c4fe81c5-b558-4474-8c15-5fef3c2e0c7a",
                                         "b992b918-d6f1-4d0e-819c-ddf2daf4e662",
                                         "fee4e1c9-f52a-40cd-a899-827595b3c526"
                                     ],
    "pseudocode":  "FLOW Microflow: ExcelImporter.Column_SetCorrectRefObjectType\r\nNODES=18; EDGES=15\r\n1. START\r\n2. ACTION RetrieveAction: retrieve MxObjects from MxModelReflection.MxObjectType\r\n3. ACTION RetrieveAction: retrieve MxObject_Ref over association Column_MxObjectType_Reference from Column\r\n4. DECISION already has objecttype? expression=$MxObject_Ref != empty\r\n5. BRANCH when EnumerationCase=true\r\n  6. ACTION ListOperationAction: ListOperationAction (output=SelectionIsValid, errorHandlingType=Rollback)\r\n  7. DECISION valid? expression=$SelectionIsValid\r\n  8. BRANCH when EnumerationCase=true\r\n    9. END\r\n  10. BRANCH when EnumerationCase=false\r\n    11. NODE ExclusiveMerge: ExclusiveMerge\r\n    12. ACTION AggregateListAction: AggregateListAction (output=NrOfObjects, errorHandlingType=Rollback)\r\n    13. DECISION \u003e 2 expression=$NrOfObjects \u003e 2\r\n    14. BRANCH when EnumerationCase=true\r\n      15. ACTION ChangeObjectAction: change Column (Column_MxObjectType_Reference=empty; refreshInClient=true)\r\n      16. END\r\n    17. BRANCH when EnumerationCase=false\r\n      18. LOOP iterate MxObjects as Iterator\r\n        19. LOOP BODY\r\n          20. NODE ContinueEvent: ContinueEvent\r\n          21. ACTION ChangeObjectAction: change Column (Column_MxObjectType_Reference=$Iterator; refreshInClient=true)\r\n          22. DECISION expression=$Iterator != $StartMxObjectType\r\n      23. ACTION MicroflowCallAction: call microflow ExcelImporter.Ch_SetObjectType_Reference\r\n      24. END\r\n25. BRANCH when EnumerationCase=false\r\n  26. REF ExclusiveMerge",
    "retrieveActions":  [
                            null
                        ],
    "decisionActions":  [
                            null
                        ],
    "showPageActions":  [
                            null
                        ],
    "mutationActions":  [
                            null
                        ],
    "callEdges":  [
                      {
                          "callerModule":  "ExcelImporter",
                          "callerFlow":  "ExcelImporter.Ch_Column_SetDefaultObject",
                          "callerKind":  "Microflow",
                          "callKind":  "Microflow",
                          "sourceNodeId":  "1bffdd8a-bdd8-4ffc-99d0-74700f597993",
                          "targetModule":  "ExcelImporter",
                          "targetFlow":  "ExcelImporter.Column_SetCorrectRefObjectType",
                          "isInternal":  true
                      },
                      {
                          "callerModule":  "ExcelImporter",
                          "callerFlow":  "ExcelImporter.Ch_FindReference",
                          "callerKind":  "Microflow",
                          "callKind":  "Microflow",
                          "sourceNodeId":  "68dd03c8-a4ee-4c87-8ff1-2d7704da433c",
                          "targetModule":  "ExcelImporter",
                          "targetFlow":  "ExcelImporter.Column_SetCorrectRefObjectType",
                          "isInternal":  true
                      },
                      {
                          "callerModule":  "ExcelImporter",
                          "callerFlow":  "ExcelImporter.Column_SetCorrectRefObjectType",
                          "callerKind":  "Microflow",
                          "callKind":  "Microflow",
                          "sourceNodeId":  "b992b918-d6f1-4d0e-819c-ddf2daf4e662",
                          "targetModule":  "ExcelImporter",
                          "targetFlow":  "ExcelImporter.Ch_SetObjectType_Reference",
                          "isInternal":  true
                      }
                  ]
}
