{
    "_meta":  {
                  "objectType":  "flow",
                  "module":  "MxModelReflection",
                  "qualifiedName":  "MxModelReflection.Ch_Reference",
                  "stableId":  "90bffadb-7767-4313-b35a-ee92ffa11967",
                  "slug":  "mxmodelreflection-ch-reference",
                  "l0Path":  "knowledge-base/modules/_marktplace/MxModelReflection/flows/mxmodelreflection-ch-reference.abstract.md",
                  "l1Path":  "knowledge-base/modules/_marktplace/MxModelReflection/flows/mxmodelreflection-ch-reference.overview.md",
                  "l2Path":  "app-overview/current/modules/marketplace/MxModelReflection/flows/mxmodelreflection-ch-reference.json",
                  "l2Logical":  "flow:MxModelReflection.Ch_Reference",
                  "sourceRun":  "cli_2026-03-14T09-26-12.835Z",
                  "aggregateJson":  "app-overview/cli_2026-03-14T09-26-12.835Z/modules/marketplace/MxModelReflection/flows.json",
                  "aggregatePseudo":  "app-overview/cli_2026-03-14T09-26-12.835Z/modules/marketplace/MxModelReflection/flows.pseudo.txt",
                  "collectionIndex":  "app-overview/current/modules/marketplace/MxModelReflection/flows/INDEX.json"
              },
    "flowId":  "90bffadb-7767-4313-b35a-ee92ffa11967",
    "kind":  "Microflow",
    "qualifiedName":  "MxModelReflection.Ch_Reference",
    "module":  "MxModelReflection",
    "nodes":  [
                  {
                      "nodeId":  "8a960d05-e30c-4c7c-9075-07570e7bfba8",
                      "nodeType":  "ActionActivity",
                      "label":  "ChangeObjectAction: change Token (FindReference=$MxObjectReference/CompleteName; refreshInClient=true)",
                      "detail":  "change Token (FindReference=$MxObjectReference/CompleteName; refreshInClient=true)",
                      "loopOwnerId":  null,
                      "isExecutable":  true,
                      "calls":  [

                                ]
                  },
                  {
                      "nodeId":  "c6e72235-dafa-4b00-a81e-995795c45566",
                      "nodeType":  "ActionActivity",
                      "label":  "RetrieveAction: retrieve MxObjectReference over association Token_MxObjectReference from Token",
                      "detail":  "retrieve MxObjectReference over association Token_MxObjectReference from Token",
                      "loopOwnerId":  null,
                      "isExecutable":  true,
                      "calls":  [

                                ]
                  },
                  {
                      "nodeId":  "be62b7b8-cefb-4054-9b1b-eb417da16a92",
                      "nodeType":  "EndEvent",
                      "label":  "EndEvent",
                      "detail":  null,
                      "loopOwnerId":  null,
                      "isExecutable":  true,
                      "calls":  [

                                ]
                  },
                  {
                      "nodeId":  "dc0552cc-026c-493b-8100-c08b62b213df",
                      "nodeType":  "MicroflowParameterObject",
                      "label":  "MicroflowParameterObject",
                      "detail":  null,
                      "loopOwnerId":  null,
                      "isExecutable":  false,
                      "calls":  [

                                ]
                  },
                  {
                      "nodeId":  "b5888ad5-07ab-4626-b84f-ec7c07996f62",
                      "nodeType":  "StartEvent",
                      "label":  "StartEvent",
                      "detail":  null,
                      "loopOwnerId":  null,
                      "isExecutable":  true,
                      "calls":  [

                                ]
                  }
              ],
    "edges":  [
                  {
                      "edgeId":  "109d73e8-a0d1-437e-b9b0-c9c5dcf09dd5",
                      "originNodeId":  "b5888ad5-07ab-4626-b84f-ec7c07996f62",
                      "destinationNodeId":  "c6e72235-dafa-4b00-a81e-995795c45566",
                      "condition":  null,
                      "isErrorHandler":  false,
                      "originConnectionIndex":  1,
                      "destinationConnectionIndex":  3
                  },
                  {
                      "edgeId":  "8f661831-2dfa-4d63-a5db-fae62a6d760e",
                      "originNodeId":  "c6e72235-dafa-4b00-a81e-995795c45566",
                      "destinationNodeId":  "8a960d05-e30c-4c7c-9075-07570e7bfba8",
                      "condition":  null,
                      "isErrorHandler":  false,
                      "originConnectionIndex":  1,
                      "destinationConnectionIndex":  3
                  },
                  {
                      "edgeId":  "3c25eb49-70d1-4e8c-b8f8-e1769a323c3c",
                      "originNodeId":  "8a960d05-e30c-4c7c-9075-07570e7bfba8",
                      "destinationNodeId":  "be62b7b8-cefb-4054-9b1b-eb417da16a92",
                      "condition":  null,
                      "isErrorHandler":  false,
                      "originConnectionIndex":  1,
                      "destinationConnectionIndex":  3
                  }
              ],
    "calls":  [

              ],
    "startNodeIds":  [
                         "b5888ad5-07ab-4626-b84f-ec7c07996f62"
                     ],
    "primaryExecutionOrderNodeIds":  [
                                         "b5888ad5-07ab-4626-b84f-ec7c07996f62",
                                         "c6e72235-dafa-4b00-a81e-995795c45566",
                                         "8a960d05-e30c-4c7c-9075-07570e7bfba8",
                                         "be62b7b8-cefb-4054-9b1b-eb417da16a92"
                                     ],
    "pseudocode":  "FLOW Microflow: MxModelReflection.Ch_Reference\r\nNODES=5; EDGES=3\r\n1. START\r\n2. ACTION RetrieveAction: retrieve MxObjectReference over association Token_MxObjectReference from Token\r\n3. ACTION ChangeObjectAction: change Token (FindReference=$MxObjectReference/CompleteName; refreshInClient=true)\r\n4. END",
    "retrieveActions":  [
                            null
                        ],
    "decisionActions":  [
                            null
                        ],
    "showPageActions":  [
                            null
                        ],
    "mutationActions":  [
                            null
                        ],
    "callEdges":  [

                  ]
}
